autocomp/__init__.py
unittest_autocomp-0.0.1.dist-info/METADATA
unittest_autocomp-0.0.1.dist-info/WHEEL
unittest_autocomp-0.0.1.dist-info/entry_points.txt
unittest_autocomp-0.0.1.dist-info/top_level.txt
unittest_autocomp-0.0.1.dist-info/RECORD
