Metadata-Version: 2.1
Name: unittest-autocomp
Version: 0.0.1
Summary: Autocompletion for unittest in Python
Home-page: https://github.com/M0r13n/unittest-autocomp
Author: Leon Morten Richter
Author-email: misc@leonmortenrichter.de
License: MIT
Keywords: test,unittest,autocompletion
Platform: UNKNOWN
Classifier: Programming Language :: Python :: 3
Classifier: License :: OSI Approved :: MIT License
Classifier: Operating System :: OS Independent
Classifier: Intended Audience :: Developers
Classifier: Typing :: Typed
Requires-Python: >=3.7
Provides-Extra: dev
Requires-Dist: coverage ; extra == 'dev'
Requires-Dist: flake8 ; extra == 'dev'
Requires-Dist: mypy ; extra == 'dev'
Requires-Dist: twine ; extra == 'dev'
